fastdetect.py
fastdetect-1.0.8.dist-info/METADATA
fastdetect-1.0.8.dist-info/WHEEL
fastdetect-1.0.8.dist-info/entry_points.txt
fastdetect-1.0.8.dist-info/license_files/LICENSE
fastdetect-1.0.8.dist-info/RECORD
