Metadata-Version: 2.1
Name: fastdetect
Version: 1.0.8
Summary: A lightweight language detection server
Project-URL: Docker Hub, https://hub.docker.com/r/kawright1989/fastdetect
Project-URL: GitHub Repository, https://github.com/kawright/fast-detect
Author-email: "Kristoffer A. Wright" <kris.al.wright@gmail.com>
Classifier: Development Status :: 4 - Beta
Classifier: Intended Audience :: Developers
Classifier: Intended Audience :: System Administrators
Classifier: License :: OSI Approved :: MIT License
Classifier: Operating System :: OS Independent
Classifier: Programming Language :: Python :: 3
Requires-Dist: bottle
Requires-Dist: fasttext
Requires-Dist: gunicorn
